pyphoon/__init__.py
pyphoon/eda_jma.py
pyphoon/visualize.py
pyphoon/clean/__init__.py
pyphoon/clean/correction.py
pyphoon/clean/detection.py
pyphoon/clean/fillgaps.py
pyphoon/clean/fix.py
pyphoon/io/__init__.py
pyphoon/io/h5.py
pyphoon/io/tsv.py
pyphoon/io/typhoonlist.py
pyphoon/io/utils.py
pyphoon/utils/__init__.py
pyphoon/utils/eda_jma.py
pyphoon-0.1.dist-info/DESCRIPTION.rst
pyphoon-0.1.dist-info/METADATA
pyphoon-0.1.dist-info/RECORD
pyphoon-0.1.dist-info/WHEEL
pyphoon-0.1.dist-info/metadata.json
pyphoon-0.1.dist-info/top_level.txt
