Metadata-Version: 2.0
Name: pyphoon
Version: 0.1
Summary: Python interface with Digital Typhoon dataset
Home-page: https://github.com/lucasrodes/pyphoon
Author: Kitamoto Lab interns
Author-email: hi@lcsrg.me
License: UNKNOWN
Download-URL: https://github.com/lucasrodes/pyphoon/archive/0.1.tar.gz
Keywords: testing,logging,example
Platform: UNKNOWN
